taylorism/__init__.py
taylorism/examples.py
taylorism/schedulers.py
taylorism/util.py
taylorism-1.1.0.dist-info/LICENSE-en.txt
taylorism-1.1.0.dist-info/LICENSE.txt
taylorism-1.1.0.dist-info/METADATA
taylorism-1.1.0.dist-info/WHEEL
taylorism-1.1.0.dist-info/top_level.txt
taylorism-1.1.0.dist-info/RECORD
