Metadata-Version: 2.1
Name: taylorism
Version: 1.1.0
Summary: Framework for parallelisation of tasks
Author-email: The Vortex Team <vortex.support@meteo.fr>
License: CECILL-C
Project-URL: repository, https://github.com/UMR-CNRM/taylorism
Classifier: Development Status :: 4 - Beta
Classifier: License :: CeCILL-C Free Software License Agreement (CECILL-C)
Requires-Python: >=3.7
License-File: LICENSE-en.txt
License-File: LICENSE.txt
Requires-Dist: bronx
Requires-Dist: footprints
Provides-Extra: docs
Requires-Dist: sphinx ; extra == 'docs'
Provides-Extra: tests
Requires-Dist: numpy ; extra == 'tests'
